MANIFEST.in
setup.py
lab/__init__.py
lab/context_processors.py
lab/metadata.py
lab/models.py
lab/plugin.py
lab/urls.py
lab/views.py
lab/migrations/0001_initial.py
lab/migrations/0002_auto_20161127_1849.py
lab/migrations/0003_auto_20161127_1952.py
lab/migrations/0004_auto_20161206_1255.py
lab/migrations/0005_auto_20161219_1110.py
lab/migrations/__init__.py
lab/templates/forms/lab_test_form.html
lab/templates/lab/_helpers/result_input.html
lab/templates/lab/_helpers/result_radio.html
lab/templates/lab/forms/form_base.html
lab/templates/lab/forms/observations/observation_base.html
lab/templates/lab/records/record_base.html
lab/templates/records/lab_test.html
lab/templatetags/__init__.py
lab/templatetags/lab_tags.py
lab/tests/__init__.py
lab/tests/dummy_options_module.py
lab/tests/models.py
lab/tests/test_context_processors.py
lab/tests/test_metadata.py
lab/tests/test_models.py
lab/tests/test_templatetags_labs.py
lab/tests/test_views.py
opal_lab.egg-info/PKG-INFO
opal_lab.egg-info/SOURCES.txt
opal_lab.egg-info/dependency_links.txt
opal_lab.egg-info/requires.txt
opal_lab.egg-info/top_level.txt