Metadata-Version: 1.0
Name: opal-lab
Version: 0.2
Summary: The lab OPAL Plugin
Home-page: http://opal.openhealthcare.org.uk/
Author: Open Health Care UK
Author-email: hello@openhealthcare.org.uk
License: LICENSE
Platform: UNKNOWN
